pyueye/__init__.py
pyueye/dll.py
pyueye/ueye.py
pyueye/ueye_tools.py
pyueye-4.90.0.0.dist-info/DESCRIPTION.rst
pyueye-4.90.0.0.dist-info/METADATA
pyueye-4.90.0.0.dist-info/RECORD
pyueye-4.90.0.0.dist-info/WHEEL
pyueye-4.90.0.0.dist-info/metadata.json
pyueye-4.90.0.0.dist-info/top_level.txt
