Metadata-Version: 2.0
Name: pyueye
Version: 4.90.0.0
Summary: pyueye - Python bindings for uEye API.
Home-page: http://www.ids-imaging.com
Author: IDS Imaging Development Systems GmbH
Author-email: info@ids-imaging.com
License: 3-Clause BSD License
Platform: UNKNOWN
Requires-Dist: enum34
